{
  "prj_name": "blog",
  "is_dev": true,
  "idc": "",

  "log": {
    "level": 5,
    "async_queue_size": 1000000,
    "buf_size": 4096
  },

  "pprof": {
    "online_enable_host": "",
    "port": ""
  },

  "api_http": {
    "gohttp_host": "",
    "gohttp_port": ""
  },

  "redis": [
    {
      "host": "",
      "pass": "",
      "port": "",
      "log_level": 7,
      "connect_timeout_seconds": 3,
      "rw_timeout_seconds": 3,
      "pool_size": 256,
      "pool_keepalive_interval_seconds": 10,
      "pool_client_max_idle_seconds": 30
    }
  ],

  "mysql": {
    "host": "",
    "user": "",
    "pass": "",
    "port": "",
    "name": "",
    "log_level": 7,
    "rw_timeout_seconds": 3,
    "pool_size": 256,
    "pool_client_max_idle_seconds": 10
  },

  "tcloud_account": {
    "app_id": "",
    "uin": "",
    "sub_account_uin": "",
    "secret_id": "",
    "secret_key": "",
    "cos_host": ""
  }
}
